timeset/__init__.py
timeset/awareness.py
timeset/continuous.py
timeset/date_range.py
timeset/daterange.py
timeset/month.py
timeset/tests.py
timeset/timerange.py
timeset/timeset.py
timeset/utils.py
timeset-0.20.dist-info/LICENSE
timeset-0.20.dist-info/METADATA
timeset-0.20.dist-info/WHEEL
timeset-0.20.dist-info/top_level.txt
timeset-0.20.dist-info/RECORD
